AUTHORS
LICENSE
MANIFEST.in
README.rst
RELEASES.rst
ROADMAP.rst
setup.py
tests/__init__.py
tests/run_tests.py
tests/settings.py
tests/urls.py
tests/urls_without_lang_prefix.py
tests/garfield/__init__.py
tests/garfield/admin.py
tests/garfield/models.py
tests/garfield/tests.py
tests/garfield/urls.py
tests/garfield/views.py
transurlvania/__init__.py
transurlvania/choices.py
transurlvania/context_processors.py
transurlvania/decorators.py
transurlvania/defaults.py
transurlvania/middleware.py
transurlvania/settings.py
transurlvania/translators.py
transurlvania/urlresolvers.py
transurlvania/utils.py
transurlvania/views.py
transurlvania.egg-info/PKG-INFO
transurlvania.egg-info/SOURCES.txt
transurlvania.egg-info/dependency_links.txt
transurlvania.egg-info/requires.txt
transurlvania.egg-info/top_level.txt
transurlvania/templatetags/__init__.py
transurlvania/templatetags/transurlvania_tags.py