Metadata-Version: 1.0
Name: transurlvania
Version: 0.2.4
Summary: This application provides a collection of URL-related utilities for multi-lingual projects.
Home-page: https://github.com/trapeze/transurlvania
Author: Sam Bull
Author-email: sam@pocketuniverse.ca
License: UNKNOWN
Platform: UNKNOWN
Classifier: Framework :: Django
Classifier: Environment :: Web Environment
Classifier: Programming Language :: Python
Classifier: Intended Audience :: Developers
Classifier: Operating System :: OS Independent
Classifier: License :: OSI Approved :: BSD License
Classifier: Topic :: Software Development :: Libraries :: Python Modules
